setup.cfg
setup.py
testpkg.py
python_testpkg.egg-info/PKG-INFO
python_testpkg.egg-info/SOURCES.txt
python_testpkg.egg-info/dependency_links.txt
python_testpkg.egg-info/entry_points.txt
python_testpkg.egg-info/top_level.txt