Metadata-Version: 1.1
Name: python-testpkg
Version: 0.3
Summary: Run test package.
Home-page: https://github.com/weijarz/python-testpkg
Author: weijarz
Author-email: weijarz@gmail.com
License: MIT
Keywords: unittest test testrunner
Platform: UNKNOWN
Classifier: Development Status :: 3 - Alpha
Classifier: Environment :: Console
Classifier: Intended Audience :: Developers
Classifier: Topic :: Software Development :: Testing
Classifier: License :: OSI Approved :: MIT License
Classifier: Operating System :: OS Independent
Classifier: Programming Language :: Python :: 3.2
Classifier: Programming Language :: Python :: 3.3
Classifier: Programming Language :: Python :: 3.4
